drupal_api/__init__.py
drupal_api/drupal.py
drupal_api/drupal_entity.py
drupal_api/drupal_field_text_formatted_long_summary.py
drupal_api/drupal_media_image.py
drupal_api/drupal_node.py
drupal_api/drupal_paragraph.py
drupal_api/drupal_redirect.py
drupal_api/drupal_taxonomy_term.py
drupal_api-0.3.dist-info/METADATA
drupal_api-0.3.dist-info/WHEEL
drupal_api-0.3.dist-info/top_level.txt
drupal_api-0.3.dist-info/RECORD
