Metadata-Version: 2.1
Name: drupal-api
Version: 0.3
Summary: A Python package for working with the Drupal REST API
Home-page: UNKNOWN
Author: Suraj Ho
Author-email: suraj@ho-sting.com
License: UNKNOWN
Platform: UNKNOWN
Requires-Dist: fake-useragent
